rf_string/__init__.py
rf_string/exceptions.py
rf_string/formatter.py
rf_string/rf_string.py
rf_string-0.1.1.dist-info/LICENSE
rf_string-0.1.1.dist-info/METADATA
rf_string-0.1.1.dist-info/WHEEL
rf_string-0.1.1.dist-info/RECORD
